{
  "_comment": "客戶 4711 的範例活動資料 — 供提示詞④執行軌跡演練、u-7 測試 mock 使用",
  "name": "Lin Wei-Chen",
  "from": "2025-06-01T00:00:00Z",
  "to": "2026-05-31T23:59:59Z",
  "trips": [
    { "from": "TPE", "to": "NRT", "departure": "2025-07-12T09:30:00Z", "arrival": "2025-07-12T13:45:00Z", "amount": 820.0 },
    { "from": "NRT", "to": "TPE", "departure": "2025-07-18T15:10:00Z", "arrival": "2025-07-18T18:05:00Z", "amount": 790.0 },
    { "from": "TPE", "to": "SIN", "departure": "2025-10-03T08:00:00Z", "arrival": "2025-10-03T12:40:00Z", "amount": 460.0 },
    { "from": "SIN", "to": "TPE", "departure": "2025-10-09T19:20:00Z", "arrival": "2025-10-09T23:55:00Z", "amount": 455.0 },
    { "from": "TPE", "to": "CDG", "departure": "2026-02-14T23:40:00Z", "arrival": "2026-02-15T08:30:00Z", "amount": 1980.0 },
    { "from": "CDG", "to": "TPE", "departure": "2026-02-28T11:10:00Z", "arrival": "2026-03-01T06:50:00Z", "amount": 1875.0 },
    { "from": "TPE", "to": "HKG", "departure": "2026-04-21T07:50:00Z", "arrival": "2026-04-21T09:35:00Z", "amount": 210.0 },
    { "from": "HKG", "to": "TPE", "departure": "2026-04-23T20:30:00Z", "arrival": "2026-04-23T22:15:00Z", "amount": 205.0 }
  ],
  "_expected": {
    "totalSpend": 6795.0,
    "tripCount": 8,
    "tripsPerYearApprox": 8.0,
    "highSpender": true,
    "frequentTraveler": false
  }
}
